pygrocydm/__init__.py
pygrocydm/grocy_api.py
pygrocydm/grocy_api_client.py
pygrocydm/grocy_datamanager.py
pygrocydm/recipes.py
pygrocydm/system.py
pygrocydm/tasks.py
pygrocydm/utils.py
test/__init__.py
test/test_battery.py
test/test_chore.py
test/test_const.py
test/test_equipment.py
test/test_grocy_datamanager.py
test/test_location.py
test/test_meal_plan.py
test/test_product.py
test/test_product_group.py
test/test_quantity_unit.py
test/test_quantity_unit_conversion.py
test/test_recipe.py
test/test_recipe_nesting.py
test/test_recipe_pos.py
test/test_recipes.py
test/test_shoppinglist.py
test/test_system.py
test/test_task.py
test/test_task_category.py
test/test_tasks.py
test/test_userentity.py
test/test_userfield.py
test/test_userobject.py
test/test_utils.py
pygrocydm-0.8.0.dist-info/LICENSE
pygrocydm-0.8.0.dist-info/METADATA
pygrocydm-0.8.0.dist-info/WHEEL
pygrocydm-0.8.0.dist-info/top_level.txt
pygrocydm-0.8.0.dist-info/RECORD
