Metadata-Version: 2.1
Name: pygrocydm
Version: 0.8.0
Summary: UNKNOWN
Home-page: https://github.com/BlueBlueBlob/pygrocydm
Author: Blueblueblob
License: MIT
Platform: UNKNOWN
Classifier: Programming Language :: Python :: 3
Classifier: License :: OSI Approved :: MIT License
Classifier: Operating System :: OS Independent
Requires-Dist: requests
Requires-Dist: iso8601
Requires-Dist: pytz
Requires-Dist: tzlocal
